notcologger/__init__.py
notcologger-0.2.1.dist-info/LICENSE
notcologger-0.2.1.dist-info/METADATA
notcologger-0.2.1.dist-info/WHEEL
notcologger-0.2.1.dist-info/entry_points.txt
notcologger-0.2.1.dist-info/RECORD
