Metadata-Version: 2.1
Name: notcologger
Version: 0.2.1
Summary: Not CO Logger, a cloud logging library.
Home-page: https://github.com/jmtapio/not-co-logger
License: MIT
Author: Juha-Matti Tapio
Author-email: jmtapio@verkkotelakka.net
Requires-Python: >=3.9,<4.0
Classifier: License :: OSI Approved :: MIT License
Classifier: Programming Language :: Python :: 3
Classifier: Programming Language :: Python :: 3.9
Classifier: Programming Language :: Python :: 3.10
Classifier: Programming Language :: Python :: 3.11
Project-URL: Repository, https://github.com/jmtapio/not-co-logger
